LICENSE.txt
evo_package_anthropic/__init__.py
evo_package_anthropic/automation/api.yaml
evo_package_anthropic/automation/entity.yaml
evo_package_anthropic/control/CAnthropicApi.py
evo_package_anthropic/control/__init__.py
evo_package_anthropic/entity/EAnthropicInfo.py
evo_package_anthropic/entity/__init__.py
evo_package_anthropic/utility/UAnthropicApi.py
evo_package_anthropic/utility/__init__.py
evo_package_anthropic-2024.10.22326.dist-info/LICENSE.txt
evo_package_anthropic-2024.10.22326.dist-info/METADATA
evo_package_anthropic-2024.10.22326.dist-info/WHEEL
evo_package_anthropic-2024.10.22326.dist-info/RECORD
