Metadata-Version: 2.1
Name: evo-package-anthropic
Version: 2024.10.22326
Summary: evo-package-anthropic python
License: CC BY-NC-ND 4.0
Author: cyborg-ai-git
Author-email: 129898917+cyborg-ai-git@users.noreply.github.com
Requires-Python: >=3.10,<4.0
Classifier: License :: Other/Proprietary License
Classifier: Programming Language :: Python :: 3
Classifier: Programming Language :: Python :: 3.10
Classifier: Programming Language :: Python :: 3.11
Classifier: Programming Language :: Python :: 3.12
Requires-Dist: anthropic (>=0.30.1,<0.31.0)
Requires-Dist: evo-framework
Requires-Dist: evo-package-assistant
Requires-Dist: evo-package-chat
